scrapy_girgit/__init__.py
scrapy_girgit/handler.py
scrapy_girgit/parser.py
scrapy_girgit-0.2.2.dist-info/METADATA
scrapy_girgit-0.2.2.dist-info/WHEEL
scrapy_girgit-0.2.2.dist-info/top_level.txt
scrapy_girgit-0.2.2.dist-info/RECORD
