Metadata-Version: 2.4
Name: scrapy-girgit
Version: 0.2.2
Summary: Add your description here
Requires-Python: >=3.12
Requires-Dist: curl-cffi>=0.12.0
Requires-Dist: scrapy>=2.13.3
